<?xml version="1.0" encoding="utf-8" standalone="yes" ?>
<Window size="320,240" sizebox="0,0,0,0" caption="0,0,0,32">
    <Font name="宋体" size="14"/>
	<Font name="宋体" size="16"/>
    <VerticalLayout bkcolor="#FFF0F0F0">
        <HorizontalLayout height="33" bkcolor="#FF303030" inset="0,3,0,0">
            <Label name="title" text="JIuqu Luancher" padding="10,1,0,0" textcolor="#00FFFFFF" disabledtextcolor="#FFA7A6AA" font="0" />
            <HorizontalLayout width="27">
				<Button name="closebtn" maxheight="22" maxwidth="27" textcolor="#FF000000" disabledtextcolor="#FFA7A6AA" align="center" normalimage="close_normal.png" hotimage="close_hover.png" pushedimage="close_pressed.png" />
			</HorizontalLayout>
        </HorizontalLayout>
        <VerticalLayout inset="20,20,20,20">
            <Text name="output_line" text="正在检查更新" textcolor="#FF000000" disabledtextcolor="#FFA7A6AA" font="1" align="center"/>
			<HorizontalLayout>
				<Button name="md5" text="md5" />
				<Button name="gen_md5" text="gen_md5" />
				<Button name="unzip" text="unzip" />
				<Button name="down" text="down" />
			</HorizontalLayout>
			<Progress name="prog_stat" text="download progress" bkimage="file='bg_progress_gray.png' corner='2,2,2,2'" foreimage="file='bg_progress_blue.png' corner='2,2,2,2'"  height="34" borderround="3,3" textpadding="0,8,0,8" textcolor="#FF000000" min="0" max="100" font="1" hor="true"/>
        </VerticalLayout>
    </VerticalLayout>
</Window>
